abstract_mode.py
bot.py
characters.py
client_config.py
config.py
direct_input.py
font_loader.py
gui.py
levels.py
menu.py
test_pytest.py
utils.py
windows.py
BHBot-2.3.dist-info/LICENSE
BHBot-2.3.dist-info/METADATA
BHBot-2.3.dist-info/WHEEL
BHBot-2.3.dist-info/top_level.txt
BHBot-2.3.dist-info/RECORD
