Metadata-Version: 2.1
Name: BHBot
Version: 2.3
Home-page: https://github.com/Nick2bad4u/BHBot
Author: Nick
Author-email: 
License: Unlicense
License-File: LICENSE
